jbig2_parser-0.1.1.dist-info/METADATA
jbig2_parser-0.1.1.dist-info/WHEEL
jbig2_parser-0.1.1.dist-info/licenses/LICENSE
jbig2_parser/__init__.py
jbig2_parser/jbig2_parser.cp310-win_amd64.pyd
jbig2_parser-0.1.1.dist-info/RECORD
