Metadata-Version: 2.4
Name: jbig2_parser
Version: 0.1.1
Classifier: Programming Language :: Python :: 3
Classifier: Programming Language :: Rust
Classifier: License :: OSI Approved :: MIT License
Classifier: Topic :: Software Development :: Libraries
Classifier: Topic :: Multimedia :: Graphics :: Graphics Conversion
License-File: LICENSE
Summary: A Python library for decoding JBIG2 images using Rust.
Keywords: jbig2,image-processing,python-bindings,rust
Author: Koehler, Nils <nils.koehler1@gmx.net>
Author-email: "Koehler, Nils" <nils.koehler1@gmx.net>
License: MIT
Project-URL: homepage, https://github.com/MichailTal/jbig2_parser
Project-URL: repository, https://github.com/MichailTal/jbig2_parser
